dt_distance/__init__.py
dt_distance/data_processor.py
dt_distance/distance_calculator.py
dt_distance/path_extractor.py
dt_distance/problem_params.py
dt_distance/tree_parser.py
dt_distance/utils.py
dt_distance-0.1.4.dist-info/LICENSE
dt_distance-0.1.4.dist-info/METADATA
dt_distance-0.1.4.dist-info/WHEEL
dt_distance-0.1.4.dist-info/top_level.txt
dt_distance-0.1.4.dist-info/RECORD
